xtbwrp/__init__.py
xtbwrp/account.py
xtbwrp/api.ini
xtbwrp/client.py
xtbwrp/handler.py
xtbwrp/utils.py
xtbwrp/wrapper.py
xtbwrp-0.1.0.dist-info/LICENSE
xtbwrp-0.1.0.dist-info/METADATA
xtbwrp-0.1.0.dist-info/WHEEL
xtbwrp-0.1.0.dist-info/top_level.txt
xtbwrp-0.1.0.dist-info/RECORD
