Metadata-Version: 2.1
Name: xtbwrp
Version: 0.1.0
Summary: A wrapper for the XTB API
Author: AustrianTradingMachine
License: GNU GENERAL PUBLIC LICENSE
Project-URL: Homepage, https://github.com/AustrianTradingMachine/xtbwrp
Keywords: XTB,API,trading,finance,development
Classifier: Development Status :: 3 - Alpha
Classifier: Programming Language :: Python :: 3
Classifier: License :: OSI Approved :: GNU General Public License v3 or later (GPLv3+)
Classifier: Operating System :: OS Independent
Classifier: Intended Audience :: Developers
Classifier: Intended Audience :: Financial and Insurance Industry
Classifier: Intended Audience :: Science/Research
Classifier: Topic :: Office/Business :: Financial
Classifier: Topic :: Office/Business :: Financial :: Investment
Classifier: Topic :: Scientific/Engineering
Classifier: Topic :: Scientific/Engineering :: Information Analysis
Requires-Python: >=3.9
License-File: LICENSE
Requires-Dist: pandas >2.0.3
Requires-Dist: pytz
Requires-Dist: tzlocal
Provides-Extra: dev
Requires-Dist: pytest ; extra == 'dev'
